admincommand/__init__.py
admincommand/admin.py
admincommand/core.py
admincommand/forms.py
admincommand/management.py
admincommand/models.py
admincommand/query.py
admincommand/utils.py
admincommand/migrations/0001_initial.py
admincommand/migrations/__init__.py
admincommand/templates/admincommand/output.html
admincommand/templates/admincommand/run.html
django_admincommand-0.1.6.dist-info/METADATA
django_admincommand-0.1.6.dist-info/RECORD
django_admincommand-0.1.6.dist-info/WHEEL
django_admincommand-0.1.6.dist-info/top_level.txt
