Metadata-Version: 2.1
Name: django-admincommand
Version: 0.1.6
Summary: Execute management commands from the Django admin
Home-page: https://github.com/BackMarket/django-admincommand
Author: Anto59290
Author-email: UNKNOWN
License: UNKNOWN
Platform: UNKNOWN
Requires-Dist: django-sneak
